cyberfusion/DatabaseSupport/__init__.py
cyberfusion/DatabaseSupport/database_importation.py
cyberfusion/DatabaseSupport/database_user_grants.py
cyberfusion/DatabaseSupport/database_users.py
cyberfusion/DatabaseSupport/databases.py
cyberfusion/DatabaseSupport/engines.py
cyberfusion/DatabaseSupport/queries.py
cyberfusion/DatabaseSupport/reports.py
cyberfusion/DatabaseSupport/servers.py
cyberfusion/DatabaseSupport/tables.py
cyberfusion/DatabaseSupport/utilities.py
cyberfusion/DatabaseSupport/exceptions/__init__.py
python3_cyberfusion_database_support-3.2.0.dist-info/METADATA
python3_cyberfusion_database_support-3.2.0.dist-info/WHEEL
python3_cyberfusion_database_support-3.2.0.dist-info/top_level.txt
python3_cyberfusion_database_support-3.2.0.dist-info/RECORD
