Metadata-Version: 2.4
Name: python3-cyberfusion-database-support
Version: 3.2.0
Summary: Library for MariaDB and PostgreSQL.
Author-email: Cyberfusion <support@cyberfusion.io>
Project-URL: Source, https://github.com/CyberfusionIO/python3-cyberfusion-database-support
Requires-Dist: psycopg2-binary==2.9.10
Requires-Dist: PyMySQL==1.1.1
Requires-Dist: SQLAlchemy==2.0.40
Requires-Dist: SQLAlchemy-Utils==0.41.0
Requires-Dist: python3-cyberfusion-common~=2.12
Requires-Dist: pydantic==2.10.6
